[{"name":"render_template.action_view","payload":{"identifier":"/Users/loganwatanabe/Desktop/ChessCamp_Phase_5_Starter/app/views/home/index.html.erb","layout":"layouts/application"},"time":"2014-10-12T20:24:08-04:00","transaction_id":"0c1fba21d70f04db1cfc","end":"2014-10-12T20:24:08-04:00","children":[],"duration":2.967},{"name":"process_action.action_controller","payload":{"controller":"HomeController","action":"index","params":{"controller":"home","action":"index"},"format":"html","method":"GET","path":"/","exception":["ActionView::Template::Error","undefined method `current_database' for #\u003CActiveRecord::ConnectionAdapters::SQLite3Adapter:0x007fab85bc6d20\u003E"],"status":"500"},"time":"2014-10-12T20:24:08-04:00","transaction_id":"0c1fba21d70f04db1cfc","end":"2014-10-12T20:24:08-04:00","children":[],"duration":31.835},{"name":"process_action.action_controller.exception","payload":{"call":"ActionView::Template::Error (undefined method `current_database' for #\u003CActiveRecord::ConnectionAdapters::SQLite3Adapter:0x007fab85bc6d20\u003E)"},"time":0,"transaction_id":null,"end":0,"children":[],"duration":0.0},{"name":"process_action.action_controller.exception","payload":{"call":"app/views/layouts/application.html.erb:15:in `_app_views_layouts_application_html_erb___3646191211849910655_70187310802540'"},"time":0,"transaction_id":null,"end":0,"children":[],"duration":0.0}]